{
  "COLUMNS": [
    "YEAR",
    "COUNTDATE",
    "FISHCOUNT",
    "SPECIESID",
    "COUNTLOCATIONID",
    "COUNTLOCATION",
    "SPECIES"
  ],
  "DATA": [
    [
      2012,
      "January, 1 2012 0:00:00",
      0,
      430,
      1205,
      "Inglutalik River",
      "Coho"
    ],
    [
      2012,
      "January, 1 2012 0:00:00",
      15,
      430,
      1205,
      "Inglutalik River",
      "Coho"
    ],
    [
      2012,
      "January, 1 2012 0:00:00",
      6,
      430,
      1205,
      "Inglutalik River",
      "Coho"
    ],
    [
      2012,
      "January, 1 2012 0:00:00",
      30,
      430,
      1205,
      "Inglutalik River",
      "Coho"
    ],
    [
      2012,
      "January, 1 2012 0:00:00",
      36,
      430,
      1205,
      "Inglutalik River",
      "Coho"
    ],
    [
      2012,
      "January, 1 2012 0:00:00",
      39,
      430,
      1205,
      "Inglutalik River",
      "Coho"
    ],
    [
      2012,
      "January, 1 2012 0:00:00",
      93,
      430,
      1205,
      "Inglutalik River",
      "Coho"
    ],
    [
      2012,
      "January, 1 2012 0:00:00",
      87,
      430,
      1205,
      "Inglutalik River",
      "Coho"
    ],
    [
      2012,
      "January, 1 2012 0:00:00",
      57,
      430,
      1205,
      "Inglutalik River",
      "Coho"
    ],
    [
      2012,
      "January, 1 2012 0:00:00",
      18,
      430,
      1205,
      "Inglutalik River",
      "Coho"
    ],
    [
      2012,
      "January, 1 2012 0:00:00",
      33,
      430,
      1205,
      "Inglutalik River",
      "Coho"
    ],
    [
      2012,
      "January, 1 2012 0:00:00",
      21,
      430,
      1205,
      "Inglutalik River",
      "Coho"
    ],
    [
      2012,
      "January, 1 2012 0:00:00",
      27,
      430,
      1205,
      "Inglutalik River",
      "Coho"
    ],
    [
      2012,
      "January, 1 2012 0:00:00",
      42,
      430,
      1205,
      "Inglutalik River",
      "Coho"
    ],
    [
      2012,
      "January, 1 2012 0:00:00",
      63,
      430,
      1205,
      "Inglutalik River",
      "Coho"
    ],
    [
      2012,
      "January, 1 2012 0:00:00",
      96,
      430,
      1205,
      "Inglutalik River",
      "Coho"
    ],
    [
      2012,
      "January, 1 2012 0:00:00",
      78,
      430,
      1205,
      "Inglutalik River",
      "Coho"
    ],
    [
      2012,
      "January, 1 2012 0:00:00",
      75,
      430,
      1205,
      "Inglutalik River",
      "Coho"
    ],
    [
      2012,
      "January, 1 2012 0:00:00",
      54,
      430,
      1205,
      "Inglutalik River",
      "Coho"
    ],
    [
      2012,
      "January, 1 2012 0:00:00",
      24,
      430,
      1205,
      "Inglutalik River",
      "Coho"
    ],
    [
      2012,
      "January, 1 2012 0:00:00",
      45,
      430,
      1205,
      "Inglutalik River",
      "Coho"
    ],
    [
      2012,
      "January, 1 2012 0:00:00",
      90,
      430,
      1205,
      "Inglutalik River",
      "Coho"
    ],
    [
      2012,
      "January, 1 2012 0:00:00",
      69,
      430,
      1205,
      "Inglutalik River",
      "Coho"
    ],
    [
      2012,
      "January, 1 2012 0:00:00",
      51,
      430,
      1205,
      "Inglutalik River",
      "Coho"
    ]
  ],
  "metadata": {
    "location_id": 1205,
    "species_id": "430",
    "year": "2012",
    "totalRecords": 24,
    "totalCount": 1149,
    "source": "ADFG Commercial Dataset",
    "last_updated": "2012-12-31T00:00:00"
  }
}